boundary_curvature/__init__.py
boundary_curvature/curvature.py
boundary_curvature-0.0.1.dist-info/LICENSE
boundary_curvature-0.0.1.dist-info/METADATA
boundary_curvature-0.0.1.dist-info/WHEEL
boundary_curvature-0.0.1.dist-info/top_level.txt
boundary_curvature-0.0.1.dist-info/RECORD
